kotlin version: 2.0.21
error message: org.jetbrains.kotlin.codegen.CompilationException: Back-end (JVM) Internal error: Couldn't transform method node:
hashCode ()I:
   L0
    ALOAD 0
    GETFIELD com/example/liftrix/data/local/entity/CustomExerciseEntity.id : Ljava/lang/String;
    INVOKEVIRTUAL java/lang/String.hashCode ()I
    ISTORE 1
   L1
    ILOAD 1
    BIPUSH 31
    IMUL
    ALOAD 0
    GETFIELD com/example/liftrix/data/local/entity/CustomExerciseEntity.userId : Ljava/lang/String;
    INVOKEVIRTUAL java/lang/String.hashCode ()I
    IADD
    ISTORE 1
    ILOAD 1
    BIPUSH 31
    IMUL
    ALOAD 0
    GETFIELD com/example/liftrix/data/local/entity/CustomExerciseEntity.name : Ljava/lang/String;
    INVOKEVIRTUAL java/lang/String.hashCode ()I
    IADD
    ISTORE 1
    ILOAD 1
    BIPUSH 31
    IMUL
    ALOAD 0
    GETFIELD com/example/liftrix/data/local/entity/CustomExerciseEntity.primaryMuscleGroup : Lcom/example/liftrix/domain/model/ExerciseCategory;
    INVOKEVIRTUAL com/example/liftrix/domain/model/ExerciseCategory.hashCode ()I
    IADD
    ISTORE 1
    ILOAD 1
    BIPUSH 31
    IMUL
    ALOAD 0
    GETFIELD com/example/liftrix/data/local/entity/CustomExerciseEntity.equipment : Lcom/example/liftrix/domain/model/Equipment;
    INVOKEVIRTUAL com/example/liftrix/domain/model/Equipment.hashCode ()I
    IADD
    ISTORE 1
    ILOAD 1
    BIPUSH 31
    IMUL
    ALOAD 0
    GETFIELD com/example/liftrix/data/local/entity/CustomExerciseEntity.secondaryMuscleGroups : Ljava/util/List;
    IFNONNULL L2
    ICONST_0
    GOTO L3
   L2
    ALOAD 0
    GETFIELD com/example/liftrix/data/local/entity/CustomExerciseEntity.secondaryMuscleGroups : Ljava/util/List;
    INVOKEVIRTUAL java/lang/Object.hashCode ()I
   L3
    IADD
    ISTORE 1
    ILOAD 1
    BIPUSH 31
    IMUL
    ALOAD 0
    GETFIELD com/example/liftrix/data/local/entity/CustomExerciseEntity.difficulty : Ljava/lang/Integer;
    IFNONNULL L4
    ICONST_0
    GOTO L5
   L4
    ALOAD 0
    GETFIELD com/example/liftrix/data/local/entity/CustomExerciseEntity.difficulty : Ljava/lang/Integer;
    INVOKEVIRTUAL java/lang/Object.hashCode ()I
   L5
    IADD
    ISTORE 1
    ILOAD 1
    BIPUSH 31
    IMUL
    ALOAD 0
    GETFIELD com/example/liftrix/data/local/entity/CustomExerciseEntity.notes : Ljava/lang/String;
    IFNONNULL L6
    ICONST_0
    GOTO L7
   L6
    ALOAD 0
    GETFIELD com/example/liftrix/data/local/entity/CustomExerciseEntity.notes : Ljava/lang/String;
    INVOKEVIRTUAL java/lang/String.hashCode ()I
   L7
    IADD
    ISTORE 1
    ILOAD 1
    BIPUSH 31
    IMUL
    ALOAD 0
    GETFIELD com/example/liftrix/data/local/entity/CustomExerciseEntity.createdAt : Ljava/time/Instant;
    INVOKEVIRTUAL java/time/Instant.hashCode ()I
    IADD
    ISTORE 1
    ILOAD 1
    BIPUSH 31
    IMUL
    ALOAD 0
    GETFIELD com/example/liftrix/data/local/entity/CustomExerciseEntity.updatedAt : Ljava/time/Instant;
    INVOKEVIRTUAL java/time/Instant.hashCode ()I
    IADD
    ISTORE 1
    ILOAD 1
    BIPUSH 31
    IMUL
    ALOAD 0
    GETFIELD com/example/liftrix/data/local/entity/CustomExerciseEntity.isSynced : Z
    INVOKESTATIC java/lang/Boolean.hashCode (Z)I
    IADD
    ISTORE 1
    ILOAD 1
    BIPUSH 31
    IMUL
    ALOAD 0
    GETFIELD com/example/liftrix/data/local/entity/CustomExerciseEntity.syncVersion : I
    INVOKESTATIC java/lang/Integer.hashCode (I)I
    IADD
    ISTORE 1
    ILOAD 1
    IRETURN
   L8
    LOCALVARIABLE result I L1 L8 1
    LOCALVARIABLE this Lcom/example/liftrix/data/local/entity/CustomExerciseEntity; L0 L8 0
    MAXSTACK = 2
    MAXLOCALS = 2

File is unknown
The root cause java.lang.OutOfMemoryError was thrown at: java.base/java.util.Arrays.copyOfRange(Arrays.java:3822)
	at org.jetbrains.kotlin.codegen.TransformationMethodVisitor.visitEnd(TransformationMethodVisitor.kt:89)
	at org.jetbrains.org.objectweb.asm.MethodVisitor.visitEnd(MethodVisitor.java:783)
	at org.jetbrains.org.objectweb.asm.tree.MethodNode.accept(MethodNode.java:772)
	at org.jetbrains.kotlin.backend.jvm.codegen.ClassCodegen.generateMethod(ClassCodegen.kt:453)
	at org.jetbrains.kotlin.backend.jvm.codegen.ClassCodegen.generate(ClassCodegen.kt:168)
	at org.jetbrains.kotlin.backend.jvm.FileCodegen.lower(JvmPhases.kt:39)
	at org.jetbrains.kotlin.backend.common.phaser.PhaseFactoriesKt.createFilePhase$lambda$4(PhaseFactories.kt:71)
	at org.jetbrains.kotlin.backend.common.phaser.PhaseBuildersKt$createSimpleNamedCompilerPhase$1.phaseBody(PhaseBuilders.kt:69)
	at org.jetbrains.kotlin.backend.common.phaser.SimpleNamedCompilerPhase.phaseBody(CompilerPhase.kt:226)
	at org.jetbrains.kotlin.backend.common.phaser.AbstractNamedCompilerPhase.invoke(CompilerPhase.kt:113)
	at org.jetbrains.kotlin.backend.common.phaser.PerformByIrFilePhase.invokeSequential(performByIrFile.kt:62)
	at org.jetbrains.kotlin.backend.common.phaser.PerformByIrFilePhase.invoke(performByIrFile.kt:52)
	at org.jetbrains.kotlin.backend.common.phaser.PerformByIrFilePhase.invoke(performByIrFile.kt:38)
	at org.jetbrains.kotlin.backend.common.phaser.NamedCompilerPhase.phaseBody(CompilerPhase.kt:166)
	at org.jetbrains.kotlin.backend.common.phaser.AbstractNamedCompilerPhase.invoke(CompilerPhase.kt:113)
	at org.jetbrains.kotlin.backend.common.phaser.CompositePhase.invoke(PhaseBuilders.kt:27)
	at org.jetbrains.kotlin.backend.common.phaser.CompositePhase.invoke(PhaseBuilders.kt:14)
	at org.jetbrains.kotlin.backend.common.phaser.NamedCompilerPhase.phaseBody(CompilerPhase.kt:166)
	at org.jetbrains.kotlin.backend.common.phaser.AbstractNamedCompilerPhase.invoke(CompilerPhase.kt:113)
	at org.jetbrains.kotlin.backend.common.phaser.CompilerPhaseKt.invokeToplevel(CompilerPhase.kt:62)
	at org.jetbrains.kotlin.backend.jvm.JvmIrCodegenFactory.invokeCodegen(JvmIrCodegenFactory.kt:371)
	at org.jetbrains.kotlin.codegen.CodegenFactory.generateModule(CodegenFactory.kt:47)
	at org.jetbrains.kotlin.backend.jvm.JvmIrCodegenFactory.generateModuleInFrontendIRMode(JvmIrCodegenFactory.kt:433)
	at org.jetbrains.kotlin.cli.jvm.compiler.pipeline.JvmCompilerPipelineKt.generateCodeFromIr(jvmCompilerPipeline.kt:246)
	at org.jetbrains.kotlin.cli.jvm.compiler.pipeline.JvmCompilerPipelineKt.compileModulesUsingFrontendIrAndLightTree(jvmCompilerPipeline.kt:142)
	at org.jetbrains.kotlin.cli.jvm.K2JVMCompiler.doExecute(K2JVMCompiler.kt:148)
	at org.jetbrains.kotlin.cli.jvm.K2JVMCompiler.doExecute(K2JVMCompiler.kt:43)
	at org.jetbrains.kotlin.cli.common.CLICompiler.execImpl(CLICompiler.kt:103)
	at org.jetbrains.kotlin.cli.common.CLICompiler.execImpl(CLICompiler.kt:49)
	at org.jetbrains.kotlin.cli.common.CLITool.exec(CLITool.kt:101)
	at org.jetbrains.kotlin.incremental.IncrementalJvmCompilerRunner.runCompiler(IncrementalJvmCompilerRunner.kt:464)
	at org.jetbrains.kotlin.incremental.IncrementalJvmCompilerRunner.runCompiler(IncrementalJvmCompilerRunner.kt:73)
	at org.jetbrains.kotlin.incremental.IncrementalCompilerRunner.doCompile(IncrementalCompilerRunner.kt:506)
	at org.jetbrains.kotlin.incremental.IncrementalCompilerRunner.compileImpl(IncrementalCompilerRunner.kt:423)
	at org.jetbrains.kotlin.incremental.IncrementalCompilerRunner.compileNonIncrementally(IncrementalCompilerRunner.kt:301)
	at org.jetbrains.kotlin.incremental.IncrementalCompilerRunner.compile(IncrementalCompilerRunner.kt:129)
	at org.jetbrains.kotlin.daemon.CompileServiceImplBase.execIncrementalCompiler(CompileServiceImpl.kt:675)
	at org.jetbrains.kotlin.daemon.CompileServiceImplBase.access$execIncrementalCompiler(CompileServiceImpl.kt:92)
	at org.jetbrains.kotlin.daemon.CompileServiceImpl.compile(CompileServiceImpl.kt:1660)
	at java.base/jdk.internal.reflect.NativeMethodAccessorImpl.invoke0(Native Method)
	at java.base/jdk.internal.reflect.NativeMethodAccessorImpl.invoke(NativeMethodAccessorImpl.java:77)
	at java.base/jdk.internal.reflect.DelegatingMethodAccessorImpl.invoke(DelegatingMethodAccessorImpl.java:43)
	at java.base/java.lang.reflect.Method.invoke(Method.java:568)
	at java.rmi/sun.rmi.server.UnicastServerRef.dispatch(UnicastServerRef.java:360)
	at java.rmi/sun.rmi.transport.Transport$1.run(Transport.java:200)
	at java.rmi/sun.rmi.transport.Transport$1.run(Transport.java:197)
	at java.base/java.security.AccessController.doPrivileged(AccessController.java:712)
	at java.rmi/sun.rmi.transport.Transport.serviceCall(Transport.java:196)
	at java.rmi/sun.rmi.transport.tcp.TCPTransport.handleMessages(TCPTransport.java:587)
	at java.rmi/sun.rmi.transport.tcp.TCPTransport$ConnectionHandler.run0(TCPTransport.java:828)
	at java.rmi/sun.rmi.transport.tcp.TCPTransport$ConnectionHandler.lambda$run$0(TCPTransport.java:705)
	at java.base/java.security.AccessController.doPrivileged(AccessController.java:399)
	at java.rmi/sun.rmi.transport.tcp.TCPTransport$ConnectionHandler.run(TCPTransport.java:704)
	at java.base/java.util.concurrent.ThreadPoolExecutor.runWorker(ThreadPoolExecutor.java:1136)
	at java.base/java.util.concurrent.ThreadPoolExecutor$Worker.run(ThreadPoolExecutor.java:635)
	at java.base/java.lang.Thread.run(Thread.java:842)
Caused by: java.lang.OutOfMemoryError: GC overhead limit exceeded
	at java.base/java.util.Arrays.copyOfRange(Arrays.java:3822)
	at java.base/java.lang.StringLatin1.newString(StringLatin1.java:769)
	at java.base/java.lang.String.substring(String.java:2716)
	at org.jetbrains.org.objectweb.asm.Frame.getAbstractTypeFromDescriptor(Frame.java:332)
	at org.jetbrains.org.objectweb.asm.Frame.push(Frame.java:552)
	at org.jetbrains.org.objectweb.asm.Frame.execute(Frame.java:1026)
	at org.jetbrains.org.objectweb.asm.MethodWriter.visitFieldInsn(MethodWriter.java:999)
	at org.jetbrains.org.objectweb.asm.MethodVisitor.visitFieldInsn(MethodVisitor.java:391)
	at org.jetbrains.org.objectweb.asm.tree.FieldInsnNode.accept(FieldInsnNode.java:88)
	at org.jetbrains.org.objectweb.asm.tree.InsnList.accept(InsnList.java:144)
	at org.jetbrains.org.objectweb.asm.tree.MethodNode.accept(MethodNode.java:751)
	at org.jetbrains.kotlin.codegen.TransformationMethodVisitor.visitEnd(TransformationMethodVisitor.kt:70)
	at org.jetbrains.org.objectweb.asm.MethodVisitor.visitEnd(MethodVisitor.java:783)
	at org.jetbrains.org.objectweb.asm.tree.MethodNode.accept(MethodNode.java:772)
	at org.jetbrains.kotlin.backend.jvm.codegen.ClassCodegen.generateMethod(ClassCodegen.kt:453)
	at org.jetbrains.kotlin.backend.jvm.codegen.ClassCodegen.generate(ClassCodegen.kt:168)
	at org.jetbrains.kotlin.backend.jvm.FileCodegen.lower(JvmPhases.kt:39)
	at org.jetbrains.kotlin.backend.common.phaser.PhaseFactoriesKt.createFilePhase$lambda$4(PhaseFactories.kt:71)
	at org.jetbrains.kotlin.backend.common.phaser.PhaseFactoriesKt$$Lambda$188/0x00000218c914a2f8.invoke(Unknown Source)
	at org.jetbrains.kotlin.backend.common.phaser.PhaseBuildersKt$createSimpleNamedCompilerPhase$1.phaseBody(PhaseBuilders.kt:69)
	at org.jetbrains.kotlin.backend.common.phaser.SimpleNamedCompilerPhase.phaseBody(CompilerPhase.kt:226)
	at org.jetbrains.kotlin.backend.common.phaser.AbstractNamedCompilerPhase.invoke(CompilerPhase.kt:113)
	at org.jetbrains.kotlin.backend.common.phaser.PerformByIrFilePhase.invokeSequential(performByIrFile.kt:62)
	at org.jetbrains.kotlin.backend.common.phaser.PerformByIrFilePhase.invoke(performByIrFile.kt:52)
	at org.jetbrains.kotlin.backend.common.phaser.PerformByIrFilePhase.invoke(performByIrFile.kt:38)
	at org.jetbrains.kotlin.backend.common.phaser.NamedCompilerPhase.phaseBody(CompilerPhase.kt:166)
	at org.jetbrains.kotlin.backend.common.phaser.AbstractNamedCompilerPhase.invoke(CompilerPhase.kt:113)
	at org.jetbrains.kotlin.backend.common.phaser.CompositePhase.invoke(PhaseBuilders.kt:27)
	at org.jetbrains.kotlin.backend.common.phaser.CompositePhase.invoke(PhaseBuilders.kt:14)
	at org.jetbrains.kotlin.backend.common.phaser.NamedCompilerPhase.phaseBody(CompilerPhase.kt:166)
	at org.jetbrains.kotlin.backend.common.phaser.AbstractNamedCompilerPhase.invoke(CompilerPhase.kt:113)
	at org.jetbrains.kotlin.backend.common.phaser.CompilerPhaseKt.invokeToplevel(CompilerPhase.kt:62)


